foxrelax/__init__.py
foxrelax/api.py
foxrelax/client.py
foxrelax/config.py
foxrelax/version.txt
foxrelax/common/__init__.py
foxrelax/common/code.py
foxrelax/common/consts.py
foxrelax/common/exceptions.py
foxrelax/common/request.py
foxrelax/common/response.py
foxrelax/common/util.py
foxrelax-0.4.3.dist-info/METADATA
foxrelax-0.4.3.dist-info/WHEEL
foxrelax-0.4.3.dist-info/top_level.txt
foxrelax-0.4.3.dist-info/RECORD
