Metadata-Version: 2.1
Name: foxrelax
Version: 0.4.3
Summary: foxrelax
Home-page: https://github.com/relaxdl/foxrelax
Author: liqiang
Author-email: liqiang@g.im
License: BSD License
Keywords: foxrelax
Platform: all
Classifier: Development Status :: 1 - Planning
Classifier: Environment :: Console
Classifier: License :: OSI Approved :: BSD License
Classifier: Operating System :: OS Independent
Classifier: Programming Language :: Python :: 3.5
Classifier: Programming Language :: Python :: 3.6
Classifier: Programming Language :: Python :: 3.7
Classifier: Programming Language :: Python :: 3.8
Classifier: Topic :: Software Development :: Libraries
Requires-Dist: pandas (>=0.24.2)
Requires-Dist: numpy (>=1.22.3)
Requires-Dist: cython (>=0.29.28)
Requires-Dist: requests (>=2.22.0)
Requires-Dist: enum34 (>=1.1.10)
